{
    "categories": [
      {
        "category": "العناية بالأم والطفل",
        "subcategories": [
          {
            "subcategory": "العناية بالأم",
            "link": "https://www.nahdionline.com/ar/mom-baby-products/mommy-care"
          },
          {
            "subcategory": "الحفاضات ومستلزمات التغيير",
            "link": "https://www.nahdionline.com/ar/mom-baby-products/diapers-changing"
          },
          {
            "subcategory": "حليب الأطفال ومستلزماته",
            "link": "https://www.nahdionline.com/ar/mom-baby-products/baby-milk-accessories"
          },
          {
            "subcategory": "طعام الأطفال وأدواته",
            "link": "https://www.nahdionline.com/ar/mom-baby-products/baby-food-accessories"
          },
          {
            "subcategory": "الإستحمام ونظافة الطفل",
            "link": "https://www.nahdionline.com/ar/mom-baby-products/bathing-care"
          },
          {
            "subcategory": "أنشطة وألعاب الأطفال",
            "link": "https://www.nahdionline.com/ar/mom-baby/toys"
          },
          {
            "subcategory": "السفر والمعدات",
            "link": "https://www.nahdionline.com/ar/mom-baby-products/baby-gear-safety"
          },
          {
            "subcategory": "العناية بصحة الطفل",
            "link": "https://www.nahdionline.com/ar/mom-baby-products/baby-healthcare"
          },
          {
            "subcategory": "الملابس والأحذية",
            "link": "https://www.nahdionline.com/ar/mom-baby-products/clothes"
          },
          {
            "subcategory": "أساسيات النوم",
            "link": "https://www.nahdionline.com/ar/mom-baby-products/sleeping-room-accessories"
          },
          {
            "subcategory": "أمان وسلامة الطفل",
            "link": "https://www.nahdionline.com/ar/mom-baby-products/safety"
          }
        ]
      },
      {
        "category": "المكملات الغذائية و الفيتامينات",
        "subcategories": [
          {
            "subcategory": "تسوق حسب الحالة الصحية",
            "link": "https://www.nahdionline.com/ar/vitamins-supplements/shop-by-health-condition"
          },
          {
            "subcategory": "صحة الأطفال",
            "link": "https://www.nahdionline.com/ar/vitamins-supplements/children-s-health"
          },
          {
            "subcategory": "صحة الرجال",
            "link": "https://www.nahdionline.com/ar/vitamins-supplements/mens-health"
          },
          {
            "subcategory": "صحة السيدات",
            "link": "https://www.nahdionline.com/ar/vitamins-supplements/women-s-health"
          },
          {
            "subcategory": "صحة كبار السن",
            "link": "https://www.nahdionline.com/ar/vitamins-supplements/sensior-s-essentials"
          },
          {
            "subcategory": "الفيتامينات",
            "link": "https://www.nahdionline.com/ar/vitamins-supplements/vitamins"
          },
          {
            "subcategory": "المعادن",
            "link": "https://www.nahdionline.com/ar/vitamins-supplements/minerals"
          },
          {
            "subcategory": "المكملات الغذائية",
            "link": "https://www.nahdionline.com/ar/vitamins-supplements/supplements"
          },
          {
            "subcategory": "المكملات العشبية",
            "link": "https://www.nahdionline.com/ar/vitamins-supplements/herbal-remedies"
          }
        ]
      },
      {
        "category": "العلاجات",
        "subcategories": [
          {
            "subcategory": "صيدلي اونلاين",
            "link": "https://m.nahdi.sa/LX"
          },
          {
            "subcategory": "إستشر ممارس صحي",
            "link": "https://nahdicareclinics.sa/index.php/ar/doctors"
          },
          {
            "subcategory": "Rx علاجات",
            "link": "https://www.nahdionline.com/ar/medications/prescribed-medicines"
          },
          {
            "subcategory": "العلاجات الذاتية",
            "link": "https://www.nahdionline.com/ar/medications/self-medications"
          },
          {
            "subcategory": "الحالات النادرة",
            "link": "https://www.nahdionline.com/ar/medications/specialty-medicines"
          }
        ]
      },
      {
        "category": "العناية بالبشرة",
        "subcategories": [
          {
            "subcategory": "الغسول",
            "link": "https://www.nahdionline.com/ar/skin-care1/cleansers"
          },
          {
            "subcategory": "الترطيب",
            "link": "https://www.nahdionline.com/ar/skin-care1/moisturizers"
          },
          {
            "subcategory": "السيروم",
            "link": "https://www.nahdionline.com/ar/skin-care1/serum"
          },
          {
            "subcategory": "الماسك",
            "link": "/ar/maskbar"
          },
          {
            "subcategory": "الوقاية من الشمس",
            "link": "https://www.nahdionline.com/ar/skin-care1/sun-care"
          },
          {
            "subcategory": "العناية بالقدم",
            "link": "https://www.nahdionline.com/ar/skin-care1/foot-care"
          },
          {
            "subcategory": "أجهزة العناية بالبشرة",
            "link": "https://www.nahdionline.com/ar/skin-care1/skin-tech-tools"
          }
        ]
      },
      {
        "category": "العناية بالشعر",
        "subcategories": [
          {
            "subcategory": "الشامبو و البلسم",
            "link": "https://www.nahdionline.com/ar/hair-care1/shampoo-conditioner"
          },
          {
            "subcategory": "تغذية الشعر",
            "link": "https://www.nahdionline.com/ar/hair-care1/hair-nourishment"
          },
          {
            "subcategory": "تصفيف الشعر",
            "link": "https://www.nahdionline.com/ar/hair-care1/hair-styling"
          },
          {
            "subcategory": "إكسسوارات وفرش الشعر",
            "link": "https://www.nahdionline.com/ar/hair-care1/hair-brushes-accessories"
          },
          {
            "subcategory": "أجهزة تصفيف الشعر",
            "link": "https://www.nahdionline.com/ar/hair-care1/hair-styling-devices"
          },
          {
            "subcategory": "صبغات الشعر",
            "link": "https://www.nahdionline.com/ar/hair-care1/hair-coloring"
          },
          {
            "subcategory": "معالجات الشعر",
            "link": "#"
          },
          {
            "subcategory": "علاج الشعر و الفروة",
            "link": "https://www.nahdionline.com/ar/hair-care1/hair-scalp-treatment"
          },
          {
            "subcategory": "عناية الخبراء",
            "link": "https://www.nahdionline.com/ar/hair-care1/professional-hair-care"
          }
        ]
      },
      {
        "category": "المكياج و العدسات",
        "subcategories": [
          {
            "subcategory": "الوجه",
            "link": "https://www.nahdionline.com/ar/makeup/face"
          },
          {
            "subcategory": "العيون",
            "link": "https://www.nahdionline.com/ar/makeup/eyes"
          },
          {
            "subcategory": "الرموش",
            "link": "https://www.nahdionline.com/ar/makeup/eyelashes"
          },
          {
            "subcategory": "الشفاه",
            "link": "https://www.nahdionline.com/ar/makeup/lips"
          },
          {
            "subcategory": "فرش المكياج و الإكسسوارات",
            "link": "https://www.nahdionline.com/ar/makeup/accessories"
          },
          {
            "subcategory": "مزيلات المكياج",
            "link": "https://www.nahdionline.com/ar/makeup/make-up-removers"
          },
          {
            "subcategory": "النظارات والعدسات",
            "link": "https://www.nahdionline.com/ar/makeup/optical-lenses"
          },
          {
            "subcategory": "الأظافر",
            "link": "https://www.nahdionline.com/ar/makeup/nails"
          }
        ]
      },
      {
        "category": "العناية الشخصية",
        "subcategories": [
          {
            "subcategory": "النظافة الشخصية",
            "link": "https://www.nahdionline.com/ar/daily-essentials1/bath-body"
          },
          {
            "subcategory": "العناية بالفم والأسنان",
            "link": "https://www.nahdionline.com/ar/daily-essentials1/oral-care"
          },
          {
            "subcategory": "العناية النسائية",
            "link": "https://www.nahdionline.com/ar/daily-essentials1/feminine-care"
          },
          {
            "subcategory": "العناية الرجالية",
            "link": "https://www.nahdionline.com/ar/daily-essentials1/men-care"
          },
          {
            "subcategory": "مزيلات العرق",
            "link": "https://www.nahdionline.com/ar/daily-essentials1/deodorants"
          },
          {
            "subcategory": "مستلزمات المنزل",
            "link": "https://www.nahdionline.com/ar/daily-essentials1/hygiene"
          },
          {
            "subcategory": "مزيلات الشعر",
            "link": "https://www.nahdionline.com/ar/daily-essentials1/hair-removals"
          },
          {
            "subcategory": "العناية الجنسية",
            "link": "https://www.nahdionline.com/ar/daily-essentials1/sexual-care"
          }
        ]
      },
      {
        "category": "العناية الصحية المنزلية",
        "subcategories": [
          {
            "subcategory": "العناية بالسكري",
            "link": "https://www.nahdionline.com/ar/medical-equipments/diabetic-care"
          },
          {
            "subcategory": "التبول اللا إرادي",
            "link": "https://www.nahdionline.com/ar/medical-equipments/incontinence"
          },
          {
            "subcategory": "أجهزة مراقبة الصحة",
            "link": "https://www.nahdionline.com/ar/medical-equipments/health-monitors"
          },
          {
            "subcategory": "حلول إدارة الألم",
            "link": "https://www.nahdionline.com/ar/medical-equipments/mobility-supports"
          },
          {
            "subcategory": "الكراسي المتحركة والعكاكيز",
            "link": "https://www.nahdionline.com/ar/medical-equipments/wheelcharis-canes"
          },
          {
            "subcategory": "الإسعافات الأولية",
            "link": "https://www.nahdionline.com/ar/medical-equipments/first-aid-disposables"
          },
          {
            "subcategory": "كمامات",
            "link": "https://www.nahdionline.com/ar/medical-equipments/face-mask"
          },
          {
            "subcategory": "اللياقة والتحكم في الوزن",
            "link": "https://www.nahdionline.com/ar/medical-equipments/weight-management"
          },
          {
            "subcategory": "أجهزة مساعدات التنفس",
            "link": "https://www.nahdionline.com/ar/medical-equipments/respiratory-equipments"
          },
          {
            "subcategory": "الأجهزة الطبية المتخصصة",
            "link": "https://www.nahdionline.com/ar/medical-equipments/professional-equipments"
          },
          {
            "subcategory": "العناية بالقدم",
            "link": "https://www.nahdionline.com/ar/medical-equipments/foot-care"
          }
        ]
      },
      {
        "category": "الأغذية الصحية",
        "subcategories": [
          {
            "subcategory": "برنامج وازن حياتك",
            "link": "https://www.nahdi.sa/wazen-planner/"
          },
          {
            "subcategory": "المكملات الرياضية",
            "link": "https://www.nahdionline.com/ar/healthy-food/sport-nutrition-products"
          },
          {
            "subcategory": "العسل",
            "link": "https://www.nahdionline.com/ar/healthy-food/honey"
          },
          {
            "subcategory": "حليب مكمل غذائي",
            "link": "https://www.nahdionline.com/ar/healthy-food/nutritional-milk"
          },
          {
            "subcategory": "الفطور الصحي",
            "link": "https://www.nahdionline.com/ar/healthy-food/breakfast"
          },
          {
            "subcategory": "وجبات صحية خفيفة",
            "link": "https://www.nahdionline.com/ar/healthy-food/snacking"
          },
          {
            "subcategory": "مشروبات صحية",
            "link": "https://www.nahdionline.com/ar/healthy-food/healthy-drinks"
          },
          {
            "subcategory": "وجبات الحمية",
            "link": "https://www.nahdionline.com/ar/healthy-food/meal-replacement"
          },
          {
            "subcategory": "الطبخ الصحي",
            "link": "https://www.nahdionline.com/ar/healthy-food/healthy-cooking"
          }
        ]
      }
    ]
  }